{"stats":{"minecraft:killed_by":{"minecraft:zombie":1},"minecraft:custom":{"minecraft:time_since_rest":8680,"minecraft:crouch_one_cm":1183,"minecraft:sprint_one_cm":3604,"minecraft:play_time":9160,"minecraft:deaths":1,"minecraft:damage_taken":355,"minecraft:walk_one_cm":8232,"minecraft:sneak_time":400,"minecraft:walk_under_water_one_cm":331,"minecraft:jump":46,"minecraft:damage_dealt":23,"minecraft:leave_game":7,"minecraft:walk_on_water_one_cm":1323,"minecraft:time_since_death":8660,"minecraft:total_world_time":9160,"minecraft:swim_one_cm":2253,"minecraft:fall_one_cm":1761,"minecraft:fly_one_cm":7223},"minecraft:mined":{"minecraft:short_grass":1,"minecraft:grass_block":2,"minecraft:sand":3,"minecraft:dirt":1},"minecraft:used":{"minecraft:dirt":3,"minecraft:sand":3},"minecraft:picked_up":{"minecraft:sand":3,"minecraft:dirt":3}},"DataVersion":3700}